libsj/__init__.py
libsj/a1fibonacci.py
libsj/a2prime.py
libsj/a3palindrome.py
libsj/a4armstrong.py
libsj/a5factorial.py
libsj-0.0.1.dist-info/LICENSE
libsj-0.0.1.dist-info/METADATA
libsj-0.0.1.dist-info/WHEEL
libsj-0.0.1.dist-info/top_level.txt
libsj-0.0.1.dist-info/RECORD
