Metadata-Version: 2.1
Name: libsj
Version: 0.0.1
Summary: libsj
Author: saksham
Author-email: sakshamsjamwal@gmail.com
Keywords: arithmetic,math,mathematics,python tutorial,saksham jamwal
Classifier: Development Status :: 1 - Planning
Classifier: Intended Audience :: Developers
Classifier: Programming Language :: Python :: 3
Classifier: Operating System :: Unix
Classifier: Operating System :: MacOS :: MacOS X
Classifier: Operating System :: Microsoft :: Windows
License-File: LICENSE
